kaya_module_sdk/__init__.py
kaya_module_sdk/sdk.py
kaya_module_sdk/src/__init__.py
kaya_module_sdk/src/datatypes/__init__.py
kaya_module_sdk/src/datatypes/classifier.py
kaya_module_sdk/src/exceptions/__init__.py
kaya_module_sdk/src/exceptions/files_not_found.py
kaya_module_sdk/src/exceptions/kconstraint.py
kaya_module_sdk/src/exceptions/kit_failure.py
kaya_module_sdk/src/exceptions/kmetadata.py
kaya_module_sdk/src/exceptions/kunimplemented.py
kaya_module_sdk/src/exceptions/kvl_failure.py
kaya_module_sdk/src/exceptions/malformed_results.py
kaya_module_sdk/src/exceptions/module_not_found.py
kaya_module_sdk/src/exceptions/tests_not_found.py
kaya_module_sdk/src/exceptions/web_server_down.py
kaya_module_sdk/src/exceptions/write_failure.py
kaya_module_sdk/src/module/__init__.py
kaya_module_sdk/src/module/arguments.py
kaya_module_sdk/src/module/config.py
kaya_module_sdk/src/module/returns.py
kaya_module_sdk/src/module/template.py
kaya_module_sdk/src/testing/__init__.py
kaya_module_sdk/src/testing/kit_code.py
kaya_module_sdk/src/testing/kit_executer.py
kaya_module_sdk/src/testing/kit_harness.py
kaya_module_sdk/src/testing/kit_reporter.py
kaya_module_sdk/src/testing/ktest.py
kaya_module_sdk/src/testing/kvl_executer.py
kaya_module_sdk/src/testing/kvl_harness.py
kaya_module_sdk/src/testing/kvl_reporter.py
kaya_module_sdk/src/utils/__init__.py
kaya_module_sdk/src/utils/check.py
kaya_module_sdk/src/utils/logger.py
kaya_module_sdk/src/utils/shell.py
kaya_module_sdk/src/utils/constraints/__init__.py
kaya_module_sdk/src/utils/constraints/equal.py
kaya_module_sdk/src/utils/constraints/greater.py
kaya_module_sdk/src/utils/constraints/greater_or_equal.py
kaya_module_sdk/src/utils/constraints/length.py
kaya_module_sdk/src/utils/constraints/less.py
kaya_module_sdk/src/utils/constraints/less_or_equal.py
kaya_module_sdk/src/utils/constraints/max_len.py
kaya_module_sdk/src/utils/constraints/maximum.py
kaya_module_sdk/src/utils/constraints/min_len.py
kaya_module_sdk-2.1.15.dist-info/METADATA
kaya_module_sdk-2.1.15.dist-info/WHEEL
kaya_module_sdk-2.1.15.dist-info/entry_points.txt
kaya_module_sdk-2.1.15.dist-info/top_level.txt
kaya_module_sdk-2.1.15.dist-info/zip-safe
kaya_module_sdk-2.1.15.dist-info/RECORD
