Metadata-Version: 2.1
Name: kaya-module-sdk
Version: 2.1.15
Summary: Kaya Module SDK.
Home-page: https://wanolabs.com
Author: WanoLabs
Author-email: contact@wanolabs.com
Requires-Python: >=3.12
Requires-Dist: pandas
